{
  "tweet_id": "2054737901208863204",
  "account_handle": "RapidResponse47",
  "posted_at": "2026-05-14T01:37:45.000Z",
  "tweet_url": "https://x.com/RapidResponse47/status/2054737901208863204",
  "genre_tags": null,
  "duration_sec": 80.346,
  "like_count": 5304,
  "retweet_count": 894,
  "produced": false,
  "content_type": "interview",
  "set_to_music": false,
  "summary": "Fox News 'Hannity' interview with Secretary of State Marco Rubio aboard Air Force One on Iran's drone/missile buildup and nuclear threat. Static interview shot with Fox chyrons. TV interview clip, not produced youth content.",
  "script": [],
  "notable_text": ""
}